odoo/addons/account_avatax_sale/README.rst
odoo/addons/account_avatax_sale/__init__.py
odoo/addons/account_avatax_sale/__manifest__.py
odoo/addons/account_avatax_sale/i18n/account_avatax_sale.pot
odoo/addons/account_avatax_sale/models/__init__.py
odoo/addons/account_avatax_sale/models/account_move.py
odoo/addons/account_avatax_sale/models/partner.py
odoo/addons/account_avatax_sale/models/sale_order.py
odoo/addons/account_avatax_sale/readme/CONTRIBUTORS.rst
odoo/addons/account_avatax_sale/readme/DESCRIPTION.rst
odoo/addons/account_avatax_sale/readme/USAGE.rst
odoo/addons/account_avatax_sale/static/description/icon.png
odoo/addons/account_avatax_sale/static/description/index.html
odoo/addons/account_avatax_sale/views/partner_view.xml
odoo/addons/account_avatax_sale/views/sale_order_view.xml
odoo13_addon_account_avatax_sale-13.0.2.4.4.dist-info/METADATA
odoo13_addon_account_avatax_sale-13.0.2.4.4.dist-info/WHEEL
odoo13_addon_account_avatax_sale-13.0.2.4.4.dist-info/top_level.txt
odoo13_addon_account_avatax_sale-13.0.2.4.4.dist-info/RECORD
