Metadata-Version: 2.1
Name: odoo13-addon-account-avatax-sale
Version: 13.0.2.4.4
Summary: Sales Orders with automatic Tax application using Avatax
Home-page: https://github.com/OCA/account-fiscal-rule
Author: Fabrice Henrion, Odoo Community Association (OCA)
Author-email: support@odoo-community.org
License: AGPL-3
Platform: UNKNOWN
Classifier: Programming Language :: Python
Classifier: Framework :: Odoo
Classifier: Framework :: Odoo :: 13.0
Classifier: License :: OSI Approved :: GNU Affero General Public License v3
Classifier: Development Status :: 4 - Beta
Requires-Python: >=3.5
Requires-Dist: odoo13-addon-account-avatax
Requires-Dist: odoo (<13.1dev,>=13.0a)
